puan_rspy-0.4.2.dist-info/METADATA
puan_rspy-0.4.2.dist-info/WHEEL
puan_rspy-0.4.2.dist-info/license_files/LICENSE
puan_rspy/__init__.py
puan_rspy/puan_rspy.cpython-310-x86_64-linux-gnu.so
puan_rspy-0.4.2.dist-info/RECORD
